twspace_dl/__init__.py
twspace_dl/__main__.py
twspace_dl/api.py
twspace_dl/cookies.py
twspace_dl/twspace.py
twspace_dl/twspace_dl.py
twspace_dl-2023.7.24.1.dist-info/LICENSE
twspace_dl-2023.7.24.1.dist-info/METADATA
twspace_dl-2023.7.24.1.dist-info/WHEEL
twspace_dl-2023.7.24.1.dist-info/entry_points.txt
twspace_dl-2023.7.24.1.dist-info/RECORD
