Metadata-Version: 2.1
Name: twspace-dl
Version: 2023.7.24.1
Summary: The only tool to record Twitter spaces (yet)
License: GPL-2.0-only
Author: Ryu1845
Author-email: ryu@tpgjbo.xyz
Requires-Python: >=3.8,<4.0
Classifier: Development Status :: 5 - Production/Stable
Classifier: Environment :: Console
Classifier: Intended Audience :: End Users/Desktop
Classifier: License :: OSI Approved :: GNU General Public License v2 (GPLv2)
Classifier: Programming Language :: Python :: 3
Classifier: Programming Language :: Python :: 3.8
Classifier: Programming Language :: Python :: 3.9
Classifier: Programming Language :: Python :: 3.10
Classifier: Programming Language :: Python :: 3.11
Classifier: Topic :: Multimedia :: Sound/Audio :: Capture/Recording
Requires-Dist: mutagen (>=1.46.0,<2.0.0)
Requires-Dist: requests (>=2.26.0,<3.0.0)
